PyPoeApi/__init__.py
PyPoeApi/exception.py
PyPoeApi/poe_client.py
PyPoeApi/query.py
PyPoeApi-0.2.4.dist-info/METADATA
PyPoeApi-0.2.4.dist-info/WHEEL
PyPoeApi-0.2.4.dist-info/top_level.txt
PyPoeApi-0.2.4.dist-info/RECORD
